evolvishub_db_migration/__init__.py
evolvishub_db_migration/cli.py
evolvishub_db_migration/constants.py
evolvishub_db_migration/core.py
evolvishub_db_migration/utils.py
evolvishub_db_migration/version.py
evolvishub_db_migration/config/__init__.py
evolvishub_db_migration/config/config.py
evolvishub_db_migration/core/__init__.py
evolvishub_db_migration/core/migration_manager.py
evolvishub_db_migration/databases/__init__.py
evolvishub_db_migration/databases/base.py
evolvishub_db_migration/databases/mssql.py
evolvishub_db_migration/databases/mysql.py
evolvishub_db_migration/databases/postgresql.py
evolvishub_db_migration/databases/sqlite.py
evolvishub_db_migration/drivers/__init__.py
evolvishub_db_migration/drivers/driver_factory.py
evolvishub_db_migration/models/__init__.py
evolvishub_db_migration/models/migration.py
evolvishub_db_migration/utils/__init__.py
evolvishub_db_migration/utils/logging_config.py
evolvishub_db_migration/utils/utils.py
evolvishub_db_migration-0.1.4.dist-info/licenses/LICENSE
evolvishub_db_migration-0.1.4.dist-info/METADATA
evolvishub_db_migration-0.1.4.dist-info/WHEEL
evolvishub_db_migration-0.1.4.dist-info/entry_points.txt
evolvishub_db_migration-0.1.4.dist-info/top_level.txt
evolvishub_db_migration-0.1.4.dist-info/RECORD
